{
   "id": "ce420a76-7573-4dc4-bf9c-b573cd0c8271",
   "name": "Knarvik Mila",
   "eventstart": "13. Mai 2021",
   "generalinfo": "Klar for ein klassikar! Distansene blir arrangert for 39. gong i 2021 Er du klar for halvmila? Løp for å leve i samarbeid med Kreftforeningen.",
   "contacts": [
      {
         "name": "Tom Jensen",
         "email": "tom@jensen.no",
         "phone": "+4799999999"
      },
      {
         "name": "Jensen Tom",
         "email": "tom@jensen.no",
         "phone": "+4799999999"
      }
   ],
   "races": [
         {
            "id": 1123,
            "distance": 10.00,
            "startlocation": "Ikea Åsane",
            "starttime": "1200Z UTC 01.01.2022",
            "vertical": false,
            "children": false,
            "womenonly": false,
            "relay": false,
            "multisport": false,
            "obstaclerun": false,
            "info": ""
         },
         {
            "id": 1123,
            "distance": 5.00,
            "startlocation": "Ikea Åsane",
            "startime": "1300Z UTC 01.01.2022",
            "vertical": false,
            "children": true,
            "womenonly": false,
            "relay": false,
            "multisport": false,
            "obstaclerun": false,
            "info": ""
         }
   ],
   "location": {
      "id": 1,
      "county": "Hordaland",
      "municipality": "Bergen",
      "place": "Ikea Åsane",
      "latitude": "",
      "longitude": ""
   }
}